.gitignore
CHANGES
CMakeLists.txt
LICENSE
PROJECT.txt
README.md
add.sh
clean.sh
pyproject.toml
run.sh
setup.py
prv/dox/doxygen.cfg
prv/ext/cmake/src/main/CMakeLists.txt
prv/ext/cmake/src/main/cpp/sys.cpp
prv/ext/cmake/src/main/headers/pymembus.h
prv/ext/cmake/src/main/headers/pymembus/blank.h
prv/ext/cmake/src/main/headers/pymembus/sys.h
prv/ext/cmake/src/test/CMakeLists.txt
prv/ext/cmake/src/test/cpp/main.cpp
prv/ext/conan/conanfile.py
prv/ext/docker/Dockerfile
prv/ext/docker/docker.sh
prv/ext/gradle/build.gradle
prv/ext/gradle/settings.gradle
prv/ext/npm/src/node-main/CMakeLists.txt
prv/ext/npm/src/node-main/package.json.in
prv/ext/npm/src/node-main/cpp/main.cpp
prv/ext/npm/src/node-main/headers/pymembus.h
prv/ext/npm/src/node-main/headers/pymembus/napiwrapper.h
prv/ext/npm/src/node-test/CMakeLists.txt
prv/ext/npm/src/node-test/js/test.js
prv/ext/pip/pyproject.toml
prv/ext/pip/setup.py
prv/ext/pip/src/py/CMakeLists.txt
prv/ext/pip/src/py/cpp/main.cpp
prv/ext/pip/src/py/headers/pymembus.h
prv/ext/pip/src/py/py/__init__.py
prv/ext/pip/src/pytest/CMakeLists.txt
prv/ext/pip/src/pytest/py/rwtest.py
prv/ext/pip/src/pytest/py/test.py
prv/install/MANIFEST.txt
prv/install/info.in
prv/install/package-config.cmake.in
prv/install/pkgconfig.pc.cmake.in
prv/install/deb/postinst
prv/sh/files.sh
prv/sh/help.sh
prv/sh/info.sh
prv/sh/rbashutils.sh
prv/sh/refresh.sh
prv/sh/test.sh
prv/sh/uninstall.sh
prv/test/Dockerfile
prv/test/docker.sh
pymembus.egg-info/PKG-INFO
pymembus.egg-info/SOURCES.txt
pymembus.egg-info/dependency_links.txt
pymembus.egg-info/top_level.txt
src/libmembus.cmake
src/pybind11.cmake
src/python.cmake
src/py/CMakeLists.txt
src/py/cpp/main.cpp
src/py/headers/pymembus.h
src/py/py/__init__.py
src/pytest/CMakeLists.txt
src/pytest/py/rwtest.py
src/pytest/py/test.py