Metadata-Version: 2.1
Name: pymembus
Version: 0.1.7
Summary: Python shared memory library
Home-page: https://github.com/wheresjames/pymembus
Author: Robert Umbehant
Author-email: pymembus@wheresjames.com
License: MIT
Platform: UNKNOWN
License-File: LICENSE
